pysh/__init__.py
pysh/cmd.py
pysh/filters.py
pysh/subprocess.py
pysh/words.py
pysh_lib-0.0.2.dist-info/LICENSE
pysh_lib-0.0.2.dist-info/METADATA
pysh_lib-0.0.2.dist-info/WHEEL
pysh_lib-0.0.2.dist-info/top_level.txt
pysh_lib-0.0.2.dist-info/RECORD
