Metadata-Version: 2.1
Name: pysh-lib
Version: 0.0.2
Summary: Pythonically simple alternative to shell scripts and subprocess
Home-page: https://github.com/gnprice/pysh
Author: Greg Price
Author-email: gnprice@gmail.com
License: MIT
Project-URL: Documentation, https://github.com/gnprice/pysh/blob/master/pysh/README.md
Project-URL: Examples, https://github.com/gnprice/pysh/tree/master/example
Keywords: scripting shell subprocess cli
Platform: UNKNOWN
Classifier: Development Status :: 3 - Alpha
Classifier: License :: OSI Approved :: MIT License
Classifier: Intended Audience :: Developers
Classifier: Intended Audience :: System Administrators
Classifier: Programming Language :: Python
Classifier: Programming Language :: Python :: 3 :: Only
Classifier: Programming Language :: Python :: 3.6
Classifier: Programming Language :: Python :: 3.7
Classifier: Programming Language :: Python :: 3.8
Classifier: Operating System :: Unix
Classifier: Operating System :: POSIX
Classifier: Operating System :: POSIX :: Linux
Classifier: Operating System :: MacOS :: MacOS X
Classifier: Environment :: Console
Classifier: Environment :: No Input/Output (Daemon)
Classifier: Environment :: Web Environment
Classifier: Environment :: Other Environment
Requires-Python: >=3.6
Requires-Dist: click (>=7.0)
